README.md
setup.cfg
setup.py
minkf/__init__.py
minkf/methods.py
minkf/utils.py
minkf.egg-info/PKG-INFO
minkf.egg-info/SOURCES.txt
minkf.egg-info/dependency_links.txt
minkf.egg-info/requires.txt
minkf.egg-info/top_level.txt