Metadata-Version: 2.1
Name: minkf
Version: 0.0.5
Summary: Kalman filter, nothing more
Home-page: https://github.com/solbes/minkf
Author: Antti Solonen
Author-email: antti.solonen@gmail.com
License: MIT
Download-URL: https://github.com/solbes/minkf/archive/refs/tags/0.0.5.zip
Keywords: kalman filter,state estimation,kalman smoother
Platform: UNKNOWN
Classifier: Development Status :: 3 - Alpha
Classifier: Intended Audience :: Science/Research
Classifier: Topic :: Scientific/Engineering :: Artificial Intelligence
Classifier: License :: OSI Approved :: MIT License
Classifier: Programming Language :: Python :: 3
Provides-Extra: dev
